bb_test
